xk/ChangYing.py
xkx-0.1.0.dist-info/licenses/LICENSE
xkx-0.1.0.dist-info/METADATA
xkx-0.1.0.dist-info/WHEEL
xkx-0.1.0.dist-info/top_level.txt
xkx-0.1.0.dist-info/RECORD
