Metadata-Version: 2.4
Name: xkx
Version: 0.1.0
Summary: 先选个名字，后面慢慢写代码
Author-email: ZhaoYuanKang <1756972525@qq.com>
License: MIT License
Project-URL: Personal website, http://121.37.247.246:200/
Requires-Python: >=3.7
License-File: LICENSE
Dynamic: license-file
